dyncommands/__init__.py
dyncommands/_version.py
dyncommands/exceptions.py
dyncommands/models.py
dyncommands/parser.py
dyncommands/py.typed
dyncommands/schema.py
dyncommands/utils.py
dyncommands/schemas/command.schema.json
dyncommands/schemas/commands.schema.json
dyncommands-1.3.dist-info/LICENSE
dyncommands-1.3.dist-info/METADATA
dyncommands-1.3.dist-info/WHEEL
dyncommands-1.3.dist-info/top_level.txt
dyncommands-1.3.dist-info/RECORD
