Metadata-Version: 2.1
Name: dyncommands
Version: 1.3
Summary: Dynamic command execution, parsing, and storage.
Home-page: https://github.com/Cubicpath/dyncommands
Author: Cubicpath
Author-email: Cubicpath@pm.me
License: MIT
Platform: UNKNOWN
Classifier: Development Status :: 5 - Production/Stable
Classifier: Intended Audience :: Developers
Classifier: License :: OSI Approved :: MIT License
Classifier: Natural Language :: English
Classifier: Operating System :: OS Independent
Classifier: Programming Language :: Python :: 3 :: Only
Classifier: Programming Language :: Python :: 3.9
Classifier: Programming Language :: Python :: 3.10
Classifier: Programming Language :: Python :: Implementation :: CPython
Classifier: Topic :: Software Development :: Libraries :: Python Modules
Classifier: Typing :: Typed
Requires-Python: >=3.9
License-File: LICENSE
Requires-Dist: jsonschema (>=4.3.2)
Requires-Dist: requests (>=2.26.0)
Requires-Dist: RestrictedPython (>=5.2)
Provides-Extra: testing
Requires-Dist: pylint (>=2.12.2) ; extra == 'testing'
Requires-Dist: pytest (>=6.2.5) ; extra == 'testing'
Requires-Dist: pytest-cov (>=3.0.0) ; extra == 'testing'
Requires-Dist: tox (>=3.24.4) ; extra == 'testing'
